ganite/__init__.py
ganite/ganite.py
ganite/logger.py
ganite/version.py
ganite/datasets/__init__.py
ganite/datasets/dataset_ihdp.py
ganite/datasets/dataset_twins.py
ganite/datasets/network.py
ganite/utils/__init__.py
ganite/utils/metrics.py
ganite/utils/random.py
ganite-0.1.2.dist-info/METADATA
ganite-0.1.2.dist-info/WHEEL
ganite-0.1.2.dist-info/top_level.txt
ganite-0.1.2.dist-info/RECORD
