Metadata-Version: 2.1
Name: ganite
Version: 0.1.2
Summary: Estimation of individualized treatment effects using generative adversarial nets
Home-page: https://github.com/vanderschaarlab/mlforhealthlabpub/tree/main/alg/ganite
Author: Jinsung Yoon
Author-email: jsyoon0823@g.ucla.edu
License: BSD-3-Clause
Platform: UNKNOWN
Classifier: Programming Language :: Python :: 3
Classifier: Topic :: Scientific/Engineering :: Artificial Intelligence
Classifier: Intended Audience :: Healthcare Industry
Classifier: License :: OSI Approved :: BSD License
Classifier: Operating System :: OS Independent
Requires-Dist: googledrivedownloader
Requires-Dist: loguru
Requires-Dist: numpy
Requires-Dist: pandas
Requires-Dist: requests
Requires-Dist: scikit-learn
Requires-Dist: scipy
Requires-Dist: torch
